check_html/__init__.py
django_check_html_middleware-2021.10.1.dist-info/LICENSE
django_check_html_middleware-2021.10.1.dist-info/METADATA
django_check_html_middleware-2021.10.1.dist-info/WHEEL
django_check_html_middleware-2021.10.1.dist-info/top_level.txt
django_check_html_middleware-2021.10.1.dist-info/RECORD
