Metadata-Version: 2.1
Name: django-check-html-middleware
Version: 2021.10.1
Summary: A Django middleware to check the html created by your application (during development)
Home-page: https://github.com/guettli/django-check-html-middleware
Author: Thomas Guettler
Author-email: guettliml.django-check-html-middleware@thomas-guettler.de
License: UNKNOWN
Platform: UNKNOWN
Classifier: Environment :: Web Environment
Classifier: Framework :: Django
Classifier: Intended Audience :: Developers
Classifier: License :: OSI Approved :: MIT License
Classifier: Programming Language :: Python :: 3
License-File: LICENSE
Requires-Dist: utidylib
Requires-Dist: pytest-django
Requires-Dist: pytest-mock
Requires-Dist: Django
Requires-Dist: six
